{"Data":"Data retrieved successfully","Date":"2023-09-09T00:31:31.9397366+03:00","Type":0}
{"Data":"Data retrieved successfully","Date":"2023-09-09T00:31:32.8880089+03:00","Type":0}
{"Data":"Data retrieved successfully","Date":"2023-09-09T00:35:46.5162844+03:00","Type":0}
{"Data":"Data retrieved successfully","Date":"2023-09-09T00:35:47.3659827+03:00","Type":0}
{"Data":"Data retrieved successfully","Date":"2023-09-09T00:37:07.9078844+03:00","Type":0}
{"Data":"Data retrieved successfully","Date":"2023-09-09T00:37:08.7372664+03:00","Type":0}
{"Data":"Data retrieved successfully","Date":"2023-09-09T00:38:52.9322149+03:00","Type":0}
{"Data":"Data retrieved successfully","Date":"2023-09-09T00:38:53.7946636+03:00","Type":0}
{"Data":"Data retrieved successfully","Date":"2023-09-09T00:41:51.6677017+03:00","Type":0}
{"Data":"Data retrieved successfully","Date":"2023-09-09T00:41:52.5191353+03:00","Type":0}
{"Data":"Data retrieved successfully","Date":"2023-09-09T00:42:36.2775862+03:00","Type":0}
{"Data":"Data retrieved successfully","Date":"2023-09-09T00:42:37.092151+03:00","Type":0}
{"Data":"Data retrieved successfully","Date":"2023-09-09T00:43:47.8028814+03:00","Type":0}
{"Data":"Data retrieved successfully","Date":"2023-09-09T00:43:48.5844197+03:00","Type":0}
{"Data":"Data retrieved successfully","Date":"2023-09-09T00:54:30.3940124+03:00","Type":0}
{"Data":"Data retrieved successfully","Date":"2023-09-09T00:54:31.4644414+03:00","Type":0}
{"Data":"Data retrieved successfully","Date":"2023-09-09T00:55:15.8425756+03:00","Type":0}
{"Data":"Data retrieved successfully","Date":"2023-09-09T00:55:16.6555414+03:00","Type":0}
{"Data":"Data retrieved successfully","Date":"2023-09-09T00:56:18.4587857+03:00","Type":0}
{"Data":"Data retrieved successfully","Date":"2023-09-09T00:56:19.2520305+03:00","Type":0}
{"Data":"Data retrieved successfully","Date":"2023-09-09T00:59:49.408704+03:00","Type":0}
{"Data":"Data retrieved successfully","Date":"2023-09-09T00:59:50.2773598+03:00","Type":0}
{"Data":"Data retrieved successfully","Date":"2023-09-09T01:01:41.8941488+03:00","Type":0}
{"Data":"Data retrieved successfully","Date":"2023-09-09T01:01:42.7280645+03:00","Type":0}
