{"Data":"Log entry from Thread 9","Date":"2023-09-13T13:45:09.0362223+03:00","Type":0}
{"Data":"Log entry from Thread 6","Date":"2023-09-13T13:45:09.248467+03:00","Type":0}
{"Data":"Log entry from Thread 7","Date":"2023-09-13T13:45:09.2790085+03:00","Type":0}
{"Data":"Log entry from Thread 10","Date":"2023-09-13T13:45:09.3163206+03:00","Type":0}
{"Data":"Log entry from Thread 8","Date":"2023-09-13T13:45:09.3468651+03:00","Type":0}
{"Data":"Log entry from Thread 1","Date":"2023-09-13T13:45:09.3743296+03:00","Type":0}
{"Data":"Log entry from Thread 3","Date":"2023-09-13T13:45:09.4017087+03:00","Type":0}
{"Data":"Log entry from Thread 4","Date":"2023-09-13T13:45:09.432807+03:00","Type":0}
{"Data":"Log entry from Thread 5","Date":"2023-09-13T13:45:09.4635196+03:00","Type":0}
{"Data":"Log entry from Thread 2","Date":"2023-09-13T13:45:09.5501128+03:00","Type":0}
{"Data":"Colleges retrieved successfully","Date":"2023-09-13T13:45:14.6133867+03:00","Type":0}
{"Data":"Colleges retrieved successfully","Date":"2023-09-13T13:45:15.6388485+03:00","Type":0}
{"Data":"Teacher data retrieved successfully","Date":"2023-09-13T13:45:17.7505171+03:00","Type":0}
{"Data":"Teacher data retrieved successfully","Date":"2023-09-13T13:45:17.7871113+03:00","Type":0}
{"Data":"Colleges retrieved successfully","Date":"2023-09-13T13:45:23.9052404+03:00","Type":0}
{"Data":"Teacher data retrieved successfully","Date":"2023-09-13T13:45:25.0236786+03:00","Type":0}
{"Data":"Teacher data retrieved successfully","Date":"2023-09-13T13:45:26.1093286+03:00","Type":0}
{"Data":"Colleges retrieved successfully","Date":"2023-09-13T13:45:30.2155041+03:00","Type":0}
{"Data":"Student Data retrieved successfully","Date":"2023-09-13T13:45:32.2853285+03:00","Type":0}
{"Data":"Student Data retrieved successfully","Date":"2023-09-13T13:45:32.3278211+03:00","Type":0}
{"Data":"Colleges retrieved successfully","Date":"2023-09-13T13:45:42.4757523+03:00","Type":0}
{"Data":"Teacher data retrieved successfully","Date":"2023-09-13T13:46:52.1203834+03:00","Type":0}
{"Data":"Teacher data retrieved successfully","Date":"2023-09-13T13:46:52.19326+03:00","Type":0}
{"Data":"Colleges retrieved successfully","Date":"2023-09-13T13:46:58.2589647+03:00","Type":0}
{"Data":"Colleges retrieved successfully","Date":"2023-09-13T13:46:58.2918211+03:00","Type":0}
{"Data":"Teacher data retrieved successfully","Date":"2023-09-13T13:46:59.5950525+03:00","Type":0}
{"Data":"Teacher data retrieved successfully","Date":"2023-09-13T13:47:00.66392+03:00","Type":0}
{"Data":"Colleges retrieved successfully","Date":"2023-09-13T13:47:02.7296154+03:00","Type":0}
{"Data":"Colleges retrieved successfully","Date":"2023-09-13T13:47:03.7732283+03:00","Type":0}
{"Data":"Student Data retrieved successfully","Date":"2023-09-13T13:47:05.8217287+03:00","Type":0}
{"Data":"Student Data retrieved successfully","Date":"2023-09-13T13:47:05.8632425+03:00","Type":0}
{"Data":"Colleges retrieved successfully","Date":"2023-09-13T13:47:21.064423+03:00","Type":0}
{"Data":"Colleges retrieved successfully","Date":"2023-09-13T13:47:22.1246066+03:00","Type":0}
{"Data":"Teacher data retrieved successfully","Date":"2023-09-13T13:47:23.1859686+03:00","Type":0}
{"Data":"Teacher data retrieved successfully","Date":"2023-09-13T13:47:23.2552941+03:00","Type":0}
{"Data":"Colleges retrieved successfully","Date":"2023-09-13T13:47:28.3075618+03:00","Type":0}
{"Data":"Colleges retrieved successfully","Date":"2023-09-13T13:47:28.3434452+03:00","Type":0}
{"Data":"Student Data retrieved successfully","Date":"2023-09-13T13:47:36.4288505+03:00","Type":0}
{"Data":"Student Data retrieved successfully","Date":"2023-09-13T13:47:36.4650082+03:00","Type":0}
{"Data":"Log entry from Thread 9","Date":"2023-09-13T13:48:06.1344058+03:00","Type":0}
{"Data":"Log entry from Thread 10","Date":"2023-09-13T13:48:06.2012715+03:00","Type":0}
{"Data":"Log entry from Thread 7","Date":"2023-09-13T13:48:06.2301215+03:00","Type":0}
{"Data":"Log entry from Thread 3","Date":"2023-09-13T13:48:06.2668838+03:00","Type":0}
{"Data":"Log entry from Thread 2","Date":"2023-09-13T13:48:06.3038681+03:00","Type":0}
{"Data":"Log entry from Thread 8","Date":"2023-09-13T13:48:06.3409345+03:00","Type":0}
{"Data":"Log entry from Thread 6","Date":"2023-09-13T13:48:06.3869299+03:00","Type":0}
{"Data":"Log entry from Thread 1","Date":"2023-09-13T13:48:06.4231961+03:00","Type":0}
{"Data":"Log entry from Thread 4","Date":"2023-09-13T13:48:06.4564478+03:00","Type":0}
{"Data":"Log entry from Thread 5","Date":"2023-09-13T13:48:06.4864549+03:00","Type":0}
{"Data":"Colleges retrieved successfully","Date":"2023-09-13T13:48:12.5731711+03:00","Type":0}
{"Data":"Colleges retrieved successfully","Date":"2023-09-13T13:48:12.6534239+03:00","Type":0}
{"Data":"Teacher data retrieved successfully","Date":"2023-09-13T13:48:12.7542927+03:00","Type":0}
{"Data":"Teacher data retrieved successfully","Date":"2023-09-13T13:48:12.8222576+03:00","Type":0}
{"Data":"Colleges retrieved successfully","Date":"2023-09-13T13:48:18.8867152+03:00","Type":0}
{"Data":"Colleges retrieved successfully","Date":"2023-09-13T13:48:18.9444271+03:00","Type":0}
{"Data":"Teacher data retrieved successfully","Date":"2023-09-13T13:48:19.0263207+03:00","Type":0}
{"Data":"Teacher data retrieved successfully","Date":"2023-09-13T13:48:19.1212745+03:00","Type":0}
{"Data":"Colleges retrieved successfully","Date":"2023-09-13T13:48:25.2173912+03:00","Type":0}
{"Data":"Colleges retrieved successfully","Date":"2023-09-13T13:48:25.2791722+03:00","Type":0}
{"Data":"Teacher data retrieved successfully","Date":"2023-09-13T13:48:25.3091315+03:00","Type":0}
{"Data":"Teacher data retrieved successfully","Date":"2023-09-13T13:48:25.3423727+03:00","Type":0}
{"Data":"Colleges retrieved successfully","Date":"2023-09-13T13:48:25.3771563+03:00","Type":0}
{"Data":"Colleges retrieved successfully","Date":"2023-09-13T13:48:25.4144232+03:00","Type":0}
{"Data":"Student Data retrieved successfully","Date":"2023-09-13T13:48:31.4741355+03:00","Type":0}
{"Data":"Student Data retrieved successfully","Date":"2023-09-13T13:48:31.5404182+03:00","Type":0}
{"Data":"Colleges retrieved successfully","Date":"2023-09-13T13:48:31.5792009+03:00","Type":0}
{"Data":"Colleges retrieved successfully","Date":"2023-09-13T13:48:31.6333711+03:00","Type":0}
{"Data":"Teacher data retrieved successfully","Date":"2023-09-13T13:48:31.6707442+03:00","Type":0}
{"Data":"Teacher data retrieved successfully","Date":"2023-09-13T13:48:31.7013281+03:00","Type":0}
{"Data":"Colleges retrieved successfully","Date":"2023-09-13T13:48:31.7292775+03:00","Type":0}
{"Data":"Colleges retrieved successfully","Date":"2023-09-13T13:48:31.7580925+03:00","Type":0}
{"Data":"Course Data retrieved successfully","Date":"2023-09-13T13:48:37.8077756+03:00","Type":0}
{"Data":"Course Data retrieved successfully","Date":"2023-09-13T13:48:37.8397668+03:00","Type":0}
{"Data":"Log entry from Thread 10","Date":"2023-09-15T08:52:17.0130278+03:00","Type":0}
{"Data":"Log entry from Thread 6","Date":"2023-09-15T08:52:17.0821727+03:00","Type":0}
{"Data":"Log entry from Thread 3","Date":"2023-09-15T08:52:17.1017135+03:00","Type":0}
{"Data":"Log entry from Thread 9","Date":"2023-09-15T08:52:17.1221943+03:00","Type":0}
{"Data":"Log entry from Thread 7","Date":"2023-09-15T08:52:17.144238+03:00","Type":0}
{"Data":"Log entry from Thread 1","Date":"2023-09-15T08:52:17.1646036+03:00","Type":0}
{"Data":"Log entry from Thread 5","Date":"2023-09-15T08:52:17.1872358+03:00","Type":0}
{"Data":"Log entry from Thread 8","Date":"2023-09-15T08:52:17.2113566+03:00","Type":0}
{"Data":"Log entry from Thread 2","Date":"2023-09-15T08:52:17.2342823+03:00","Type":0}
{"Data":"Log entry from Thread 4","Date":"2023-09-15T08:52:17.2528011+03:00","Type":0}
{"Data":"Log entry from Thread 3","Date":"2023-09-15T08:55:26.8642014+03:00","Type":0}
{"Data":"Log entry from Thread 7","Date":"2023-09-15T08:55:26.8993803+03:00","Type":0}
{"Data":"Log entry from Thread 10","Date":"2023-09-15T08:55:26.921188+03:00","Type":0}
{"Data":"Log entry from Thread 9","Date":"2023-09-15T08:55:26.9429786+03:00","Type":0}
{"Data":"Log entry from Thread 8","Date":"2023-09-15T08:55:26.9637136+03:00","Type":0}
{"Data":"Log entry from Thread 5","Date":"2023-09-15T08:55:27.0153553+03:00","Type":0}
{"Data":"Log entry from Thread 6","Date":"2023-09-15T08:55:27.0396687+03:00","Type":0}
{"Data":"Log entry from Thread 4","Date":"2023-09-15T08:55:27.0600037+03:00","Type":0}
{"Data":"Log entry from Thread 2","Date":"2023-09-15T08:55:27.0808306+03:00","Type":0}
{"Data":"Log entry from Thread 1","Date":"2023-09-15T08:55:27.0989384+03:00","Type":0}
{"Data":"Log entry from Thread 8","Date":"2023-09-15T09:03:12.5196562+03:00","Type":0}
{"Data":"Log entry from Thread 4","Date":"2023-09-15T09:03:12.5667353+03:00","Type":0}
{"Data":"Log entry from Thread 5","Date":"2023-09-15T09:03:12.6032553+03:00","Type":0}
{"Data":"Log entry from Thread 7","Date":"2023-09-15T09:03:12.6268865+03:00","Type":0}
{"Data":"Log entry from Thread 6","Date":"2023-09-15T09:03:12.6481937+03:00","Type":0}
{"Data":"Log entry from Thread 9","Date":"2023-09-15T09:03:12.6720582+03:00","Type":0}
{"Data":"Log entry from Thread 3","Date":"2023-09-15T09:03:12.6946275+03:00","Type":0}
{"Data":"Log entry from Thread 10","Date":"2023-09-15T09:03:12.7157564+03:00","Type":0}
{"Data":"Log entry from Thread 2","Date":"2023-09-15T09:03:12.7381117+03:00","Type":0}
{"Data":"Log entry from Thread 1","Date":"2023-09-15T09:03:12.7579489+03:00","Type":0}
{"Data":"Log entry from Thread 2","Date":"2023-09-15T09:11:21.8240845+03:00","Type":0}
{"Data":"Log entry from Thread 7","Date":"2023-09-15T09:11:21.861135+03:00","Type":0}
{"Data":"Log entry from Thread 9","Date":"2023-09-15T09:11:21.8793989+03:00","Type":0}
{"Data":"Log entry from Thread 8","Date":"2023-09-15T09:11:21.9015314+03:00","Type":0}
{"Data":"Log entry from Thread 6","Date":"2023-09-15T09:11:21.9180542+03:00","Type":0}
{"Data":"Log entry from Thread 10","Date":"2023-09-15T09:11:21.9359465+03:00","Type":0}
{"Data":"Log entry from Thread 5","Date":"2023-09-15T09:11:21.9533855+03:00","Type":0}
{"Data":"Log entry from Thread 3","Date":"2023-09-15T09:11:21.9703138+03:00","Type":0}
{"Data":"Log entry from Thread 4","Date":"2023-09-15T09:11:21.9877381+03:00","Type":0}
{"Data":"Log entry from Thread 1","Date":"2023-09-15T09:11:22.0059947+03:00","Type":0}
{"Data":"Log entry from Thread 2","Date":"2023-09-15T09:11:53.4815925+03:00","Type":0}
{"Data":"Log entry from Thread 5","Date":"2023-09-15T09:11:53.5166387+03:00","Type":0}
{"Data":"Log entry from Thread 6","Date":"2023-09-15T09:11:53.5354968+03:00","Type":0}
{"Data":"Log entry from Thread 10","Date":"2023-09-15T09:11:53.5551163+03:00","Type":0}
{"Data":"Log entry from Thread 7","Date":"2023-09-15T09:11:53.5724356+03:00","Type":0}
{"Data":"Log entry from Thread 9","Date":"2023-09-15T09:11:53.589073+03:00","Type":0}
{"Data":"Log entry from Thread 1","Date":"2023-09-15T09:11:53.6062077+03:00","Type":0}
{"Data":"Log entry from Thread 8","Date":"2023-09-15T09:11:53.6232315+03:00","Type":0}
{"Data":"Log entry from Thread 3","Date":"2023-09-15T09:11:53.6393668+03:00","Type":0}
{"Data":"Log entry from Thread 4","Date":"2023-09-15T09:11:53.6565124+03:00","Type":0}
{"Data":"Log entry from Thread 3","Date":"2023-09-15T09:13:01.7996884+03:00","Type":0}
{"Data":"Log entry from Thread 9","Date":"2023-09-15T09:13:01.8827158+03:00","Type":0}
{"Data":"Log entry from Thread 1","Date":"2023-09-15T09:13:01.9532561+03:00","Type":0}
{"Data":"Log entry from Thread 8","Date":"2023-09-15T09:13:01.972603+03:00","Type":0}
{"Data":"Log entry from Thread 4","Date":"2023-09-15T09:13:01.9902282+03:00","Type":0}
{"Data":"Log entry from Thread 10","Date":"2023-09-15T09:13:02.0084458+03:00","Type":0}
{"Data":"Log entry from Thread 6","Date":"2023-09-15T09:13:02.0512344+03:00","Type":0}
{"Data":"Log entry from Thread 5","Date":"2023-09-15T09:13:02.0705085+03:00","Type":0}
{"Data":"Log entry from Thread 2","Date":"2023-09-15T09:13:02.0891864+03:00","Type":0}
{"Data":"Log entry from Thread 7","Date":"2023-09-15T09:13:02.1072714+03:00","Type":0}
{"Data":"Log entry from Thread 8","Date":"2023-09-15T09:14:15.9474127+03:00","Type":0}
{"Data":"Log entry from Thread 7","Date":"2023-09-15T09:14:15.9827532+03:00","Type":0}
{"Data":"Log entry from Thread 3","Date":"2023-09-15T09:14:15.9989031+03:00","Type":0}
{"Data":"Log entry from Thread 10","Date":"2023-09-15T09:14:16.0185833+03:00","Type":0}
{"Data":"Log entry from Thread 9","Date":"2023-09-15T09:14:16.0364812+03:00","Type":0}
{"Data":"Log entry from Thread 4","Date":"2023-09-15T09:14:16.0531021+03:00","Type":0}
{"Data":"Log entry from Thread 6","Date":"2023-09-15T09:14:16.0699796+03:00","Type":0}
{"Data":"Log entry from Thread 2","Date":"2023-09-15T09:14:16.0859075+03:00","Type":0}
{"Data":"Log entry from Thread 1","Date":"2023-09-15T09:14:16.1027497+03:00","Type":0}
{"Data":"Log entry from Thread 5","Date":"2023-09-15T09:14:16.1200616+03:00","Type":0}
{"Data":"Log entry from Thread 4","Date":"2023-09-15T09:16:04.4168098+03:00","Type":0}
{"Data":"Log entry from Thread 2","Date":"2023-09-15T09:16:04.4499872+03:00","Type":0}
{"Data":"Log entry from Thread 3","Date":"2023-09-15T09:16:04.4699207+03:00","Type":0}
{"Data":"Log entry from Thread 1","Date":"2023-09-15T09:16:04.4860495+03:00","Type":0}
{"Data":"Log entry from Thread 10","Date":"2023-09-15T09:16:04.502882+03:00","Type":0}
{"Data":"Log entry from Thread 5","Date":"2023-09-15T09:16:04.5195363+03:00","Type":0}
{"Data":"Log entry from Thread 6","Date":"2023-09-15T09:16:04.53882+03:00","Type":0}
{"Data":"Log entry from Thread 7","Date":"2023-09-15T09:16:04.556864+03:00","Type":0}
{"Data":"Log entry from Thread 8","Date":"2023-09-15T09:16:04.5733673+03:00","Type":0}
{"Data":"Log entry from Thread 9","Date":"2023-09-15T09:16:04.590252+03:00","Type":0}
{"Data":"Log entry from Thread 1","Date":"2023-09-15T09:18:05.7900211+03:00","Type":0}
{"Data":"Log entry from Thread 2","Date":"2023-09-15T09:18:15.8465373+03:00","Type":0}
{"Data":"Log entry from Thread 4","Date":"2023-09-15T09:18:15.8702274+03:00","Type":0}
{"Data":"Log entry from Thread 5","Date":"2023-09-15T09:18:15.8942023+03:00","Type":0}
{"Data":"Log entry from Thread 6","Date":"2023-09-15T09:18:15.9151983+03:00","Type":0}
{"Data":"Log entry from Thread 7","Date":"2023-09-15T09:18:15.934022+03:00","Type":0}
{"Data":"Log entry from Thread 8","Date":"2023-09-15T09:18:15.9522114+03:00","Type":0}
{"Data":"Log entry from Thread 9","Date":"2023-09-15T09:18:15.9726145+03:00","Type":0}
{"Data":"Log entry from Thread 10","Date":"2023-09-15T09:18:15.9954859+03:00","Type":0}
{"Data":"Log entry from Thread 3","Date":"2023-09-15T09:18:16.0162392+03:00","Type":0}
{"Data":"Log entry from Thread 9","Date":"2023-09-15T09:21:13.7627753+03:00","Type":0}
{"Data":"Log entry from Thread 3","Date":"2023-09-15T09:21:13.8133125+03:00","Type":0}
{"Data":"Log entry from Thread 4","Date":"2023-09-15T09:21:13.8338471+03:00","Type":0}
{"Data":"Log entry from Thread 2","Date":"2023-09-15T09:21:13.8665999+03:00","Type":0}
{"Data":"Log entry from Thread 10","Date":"2023-09-15T09:21:13.8897202+03:00","Type":0}
{"Data":"Log entry from Thread 8","Date":"2023-09-15T09:21:13.9092875+03:00","Type":0}
{"Data":"Log entry from Thread 1","Date":"2023-09-15T09:21:13.9285968+03:00","Type":0}
{"Data":"Log entry from Thread 7","Date":"2023-09-15T09:21:13.9470651+03:00","Type":0}
{"Data":"Log entry from Thread 6","Date":"2023-09-15T09:21:13.971481+03:00","Type":0}
{"Data":"Log entry from Thread 5","Date":"2023-09-15T09:21:13.9918735+03:00","Type":0}
{"Data":"Log entry from Thread 2","Date":"2023-09-15T09:21:48.5443025+03:00","Type":0}
{"Data":"Log entry from Thread 3","Date":"2023-09-15T09:21:57.5758733+03:00","Type":0}
{"Data":"Log entry from Thread 4","Date":"2023-09-15T09:21:57.9274926+03:00","Type":0}
{"Data":"Log entry from Thread 5","Date":"2023-09-15T09:21:58.8290493+03:00","Type":0}
{"Data":"Log entry from Thread 1","Date":"2023-09-15T09:21:59.0606267+03:00","Type":0}
{"Data":"Log entry from Thread 6","Date":"2023-09-15T09:21:59.6242339+03:00","Type":0}
{"Data":"Log entry from Thread 7","Date":"2023-09-15T09:22:00.5457896+03:00","Type":0}
{"Data":"Log entry from Thread 8","Date":"2023-09-15T09:22:00.6673597+03:00","Type":0}
{"Data":"Log entry from Thread 9","Date":"2023-09-15T09:22:01.0726689+03:00","Type":0}
{"Data":"Log entry from Thread 10","Date":"2023-09-15T09:22:01.7363518+03:00","Type":0}
{"Data":"Log entry from Thread 10","Date":"2023-09-15T09:30:25.8018177+03:00","Type":0}
{"Data":"Log entry from Thread 9","Date":"2023-09-15T09:30:26.3464994+03:00","Type":0}
{"Data":"Log entry from Thread 8","Date":"2023-09-15T09:30:26.4274847+03:00","Type":0}
{"Data":"Log entry from Thread 7","Date":"2023-09-15T09:30:26.483945+03:00","Type":0}
{"Data":"Log entry from Thread 6","Date":"2023-09-15T09:30:26.5449041+03:00","Type":0}
{"Data":"Log entry from Thread 5","Date":"2023-09-15T09:30:26.6096392+03:00","Type":0}
{"Data":"Log entry from Thread 4","Date":"2023-09-15T09:30:26.6830132+03:00","Type":0}
{"Data":"Log entry from Thread 3","Date":"2023-09-15T09:30:26.7846643+03:00","Type":0}
{"Data":"Log entry from Thread 2","Date":"2023-09-15T09:30:26.9076894+03:00","Type":0}
{"Data":"Log entry from Thread 1","Date":"2023-09-15T09:30:27.0151987+03:00","Type":0}
{"Data":"Log entry from Thread 9","Date":"2023-09-15T09:33:46.6333732+03:00","Type":0}
{"Data":"Log entry from Thread 7","Date":"2023-09-15T09:33:46.6770055+03:00","Type":0}
{"Data":"Log entry from Thread 4","Date":"2023-09-15T09:33:46.694666+03:00","Type":0}
{"Data":"Log entry from Thread 2","Date":"2023-09-15T09:33:46.7161475+03:00","Type":0}
{"Data":"Log entry from Thread 3","Date":"2023-09-15T09:33:46.7418679+03:00","Type":0}
{"Data":"Log entry from Thread 10","Date":"2023-09-15T09:33:46.7624559+03:00","Type":0}
{"Data":"Log entry from Thread 6","Date":"2023-09-15T09:33:46.7808784+03:00","Type":0}
{"Data":"Log entry from Thread 8","Date":"2023-09-15T09:33:46.7994615+03:00","Type":0}
{"Data":"Log entry from Thread 1","Date":"2023-09-15T09:33:46.8171239+03:00","Type":0}
{"Data":"Log entry from Thread 5","Date":"2023-09-15T09:33:46.8348943+03:00","Type":0}
{"Data":"Log entry from Thread 4","Date":"2023-09-15T09:36:41.118612+03:00","Type":0}
{"Data":"Log entry from Thread 8","Date":"2023-09-15T09:36:41.5297165+03:00","Type":0}
{"Data":"Log entry from Thread 7","Date":"2023-09-15T09:36:41.5861258+03:00","Type":0}
{"Data":"Log entry from Thread 6","Date":"2023-09-15T09:36:41.648098+03:00","Type":0}
{"Data":"Log entry from Thread 9","Date":"2023-09-15T09:36:41.7003603+03:00","Type":0}
{"Data":"Log entry from Thread 1","Date":"2023-09-15T09:36:41.749695+03:00","Type":0}
{"Data":"Log entry from Thread 5","Date":"2023-09-15T09:36:41.8055939+03:00","Type":0}
{"Data":"Log entry from Thread 10","Date":"2023-09-15T09:36:41.8614964+03:00","Type":0}
{"Data":"Log entry from Thread 2","Date":"2023-09-15T09:36:41.925917+03:00","Type":0}
{"Data":"Log entry from Thread 3","Date":"2023-09-15T09:36:41.9720106+03:00","Type":0}
{"Data":"Log entry from Thread 4","Date":"2023-09-15T09:41:07.3854463+03:00","Type":0}
{"Data":"Log entry from Thread 9","Date":"2023-09-15T09:41:07.4229473+03:00","Type":0}
{"Data":"Log entry from Thread 3","Date":"2023-09-15T09:41:07.4492414+03:00","Type":0}
{"Data":"Log entry from Thread 8","Date":"2023-09-15T09:41:07.4671991+03:00","Type":0}
{"Data":"Log entry from Thread 5","Date":"2023-09-15T09:41:07.4848966+03:00","Type":0}
{"Data":"Log entry from Thread 10","Date":"2023-09-15T09:41:07.5024522+03:00","Type":0}
{"Data":"Log entry from Thread 1","Date":"2023-09-15T09:41:07.5193414+03:00","Type":0}
{"Data":"Log entry from Thread 6","Date":"2023-09-15T09:41:07.5382857+03:00","Type":0}
{"Data":"Log entry from Thread 7","Date":"2023-09-15T09:41:07.5549912+03:00","Type":0}
{"Data":"Log entry from Thread 2","Date":"2023-09-15T09:41:07.5722819+03:00","Type":0}
{"Data":"Log entry from Thread 4","Date":"2023-09-15T09:42:10.2486828+03:00","Type":0}
{"Data":"Log entry from Thread 2","Date":"2023-09-15T09:42:20.2583359+03:00","Type":0}
{"Data":"Log entry from Thread 1","Date":"2023-09-15T09:42:20.2819961+03:00","Type":0}
{"Data":"Log entry from Thread 8","Date":"2023-09-15T09:42:20.3023106+03:00","Type":0}
{"Data":"Log entry from Thread 6","Date":"2023-09-15T09:42:20.3196345+03:00","Type":0}
{"Data":"Log entry from Thread 7","Date":"2023-09-15T09:42:20.3446837+03:00","Type":0}
{"Data":"Log entry from Thread 10","Date":"2023-09-15T09:42:20.3611737+03:00","Type":0}
{"Data":"Log entry from Thread 9","Date":"2023-09-15T09:42:20.3799718+03:00","Type":0}
{"Data":"Log entry from Thread 3","Date":"2023-09-15T09:42:20.3993918+03:00","Type":0}
{"Data":"Log entry from Thread 5","Date":"2023-09-15T09:42:20.4180342+03:00","Type":0}
{"Data":"Log entry from Thread 9","Date":"2023-09-15T09:53:21.0860342+03:00","Type":0}
{"Data":"Log entry from Thread 4","Date":"2023-09-15T09:53:21.8843751+03:00","Type":0}
{"Data":"Log entry from Thread 5","Date":"2023-09-15T09:53:22.0025716+03:00","Type":0}
{"Data":"Log entry from Thread 8","Date":"2023-09-15T09:53:22.1242078+03:00","Type":0}
{"Data":"Log entry from Thread 10","Date":"2023-09-15T09:53:22.2482738+03:00","Type":0}
{"Data":"Log entry from Thread 2","Date":"2023-09-15T09:53:22.334629+03:00","Type":0}
{"Data":"Log entry from Thread 6","Date":"2023-09-15T09:53:22.4229181+03:00","Type":0}
{"Data":"Log entry from Thread 7","Date":"2023-09-15T09:53:22.5104305+03:00","Type":0}
{"Data":"Log entry from Thread 3","Date":"2023-09-15T09:53:22.6544803+03:00","Type":0}
{"Data":"Log entry from Thread 1","Date":"2023-09-15T09:53:22.8252891+03:00","Type":0}
{"Data":"Log entry from Thread 1","Date":"2023-09-15T10:13:12.1338461+03:00","Type":0}
{"Data":"Log entry from Thread 10","Date":"2023-09-15T10:13:12.2781872+03:00","Type":0}
{"Data":"Log entry from Thread 6","Date":"2023-09-15T10:13:12.3081454+03:00","Type":0}
{"Data":"Log entry from Thread 2","Date":"2023-09-15T10:13:12.3417482+03:00","Type":0}
{"Data":"Log entry from Thread 9","Date":"2023-09-15T10:13:12.3762039+03:00","Type":0}
{"Data":"Log entry from Thread 8","Date":"2023-09-15T10:13:12.4096819+03:00","Type":0}
{"Data":"Log entry from Thread 7","Date":"2023-09-15T10:13:12.4471175+03:00","Type":0}
{"Data":"Log entry from Thread 3","Date":"2023-09-15T10:13:12.4803665+03:00","Type":0}
{"Data":"Log entry from Thread 4","Date":"2023-09-15T10:13:12.5121732+03:00","Type":0}
{"Data":"Log entry from Thread 5","Date":"2023-09-15T10:13:12.5460625+03:00","Type":0}
{"Data":"Log entry from Thread 10","Date":"2023-09-15T10:20:09.6329434+03:00","Type":0}
{"Data":"Log entry from Thread 8","Date":"2023-09-15T10:20:10.5039483+03:00","Type":0}
{"Data":"Log entry from Thread 9","Date":"2023-09-15T10:20:10.6519446+03:00","Type":0}
{"Data":"Log entry from Thread 2","Date":"2023-09-15T10:20:10.8970969+03:00","Type":0}
{"Data":"Log entry from Thread 5","Date":"2023-09-15T10:20:11.007665+03:00","Type":0}
{"Data":"Log entry from Thread 1","Date":"2023-09-15T10:20:11.4208815+03:00","Type":0}
{"Data":"Log entry from Thread 6","Date":"2023-09-15T10:20:11.5935703+03:00","Type":0}
{"Data":"Log entry from Thread 7","Date":"2023-09-15T10:20:11.7424025+03:00","Type":0}
{"Data":"Log entry from Thread 4","Date":"2023-09-15T10:20:11.9370933+03:00","Type":0}
{"Data":"Log entry from Thread 3","Date":"2023-09-15T10:20:12.1147526+03:00","Type":0}
{"Data":"Log entry from Thread 10","Date":"2023-09-15T10:23:46.8542557+03:00","Type":0}
{"Data":"Log entry from Thread 1","Date":"2023-09-15T10:23:46.9103418+03:00","Type":0}
{"Data":"Log entry from Thread 3","Date":"2023-09-15T10:23:46.9427238+03:00","Type":0}
{"Data":"Log entry from Thread 2","Date":"2023-09-15T10:23:46.9709209+03:00","Type":0}
{"Data":"Log entry from Thread 4","Date":"2023-09-15T10:23:47.0001773+03:00","Type":0}
{"Data":"Log entry from Thread 6","Date":"2023-09-15T10:23:47.1099327+03:00","Type":0}
{"Data":"Log entry from Thread 7","Date":"2023-09-15T10:23:47.1483809+03:00","Type":0}
{"Data":"Log entry from Thread 8","Date":"2023-09-15T10:23:47.1808414+03:00","Type":0}
{"Data":"Log entry from Thread 9","Date":"2023-09-15T10:23:47.2113489+03:00","Type":0}
{"Data":"Log entry from Thread 5","Date":"2023-09-15T10:23:47.2523127+03:00","Type":0}
